git_semver_tags/__init__.py
git_semver_tags/__main__.py
git_semver_tags/git.py
git_semver_tags/version.py
git_semver_tags-1.0.1.dist-info/LICENSE
git_semver_tags-1.0.1.dist-info/METADATA
git_semver_tags-1.0.1.dist-info/WHEEL
git_semver_tags-1.0.1.dist-info/top_level.txt
git_semver_tags-1.0.1.dist-info/RECORD
