Metadata-Version: 2.1
Name: git-semver-tags
Version: 1.0.1
Summary: Compare and read semver-like versions from git tags.
Author-email: Andrew Geiger <andrew@corsosystems.com>
Project-URL: Homepage, https://github.com/CorsoSource/git-semver-tags
Classifier: Development Status :: 4 - Beta
Classifier: Programming Language :: Python :: 3
Classifier: License :: OSI Approved :: Apache Software License
Classifier: Operating System :: OS Independent
Requires-Python: >=3.2
License-File: LICENSE
